{
  "title": "破壁与共生",
  "subtitle": "中国科技品牌日韩市场第二增长曲线深度洞察报告",
  "tagline": "从“性价比屠夫”到“生态破壁者”，探寻在成熟堡垒市场构建可持续增长的全景文章总览",
  "tocTitle": "报告目录",
  "hero": {
    "summary": "本报告融合多源深度分析，系统审视中国科技品牌在日韩市场的竞争现状、核心挑战与未来机遇。报告揭示，品牌竞争已从硬件参数比拼，升维至生态构建、文化融入与供应链韧性的综合较量。在“战略性乐观与战术性审慎”的舆论基调下，探寻以深度本土化、价值创新和战略耐心开辟第二增长曲线的可行路径。",
    "highlights": [
      "市场格局呈现“硬件受阻，软件/垂直硬件突破”的冰火交织图景，TikTok、大疆等成为破局先锋。",
      "竞争壁垒多维高企：渠道、品牌情感、法规合规与文化认知构成系统性挑战，单纯产品优势难以撼动。",
      "舆论认知完成从“沸腾期”到“恒温深耕期”的演变，情感更趋理性，关注点转向可持续本土化与长期品牌资产构建。",
      "未来增长引擎在于“形态创新 × AI原生体验 × 生态协同”的价值创造公式，以及从市场参与者向产业规则定义者的跃迁。"
    ],
    "kpis": [
      {
        "label": "日韩智能机市场本土品牌份额",
        "value": ">80%",
        "delta": "持续固化",
        "tone": "down"
      },
      {
        "label": "中国品牌研发投入强度",
        "value": "比肩巨头",
        "delta": "持续增长",
        "tone": "up"
      },
      {
        "label": "舆论情感健康度(正/负比)",
        "value": "1.6",
        "delta": "健康区间",
        "tone": "neutral"
      },
      {
        "label": "高端市场破局关键",
        "value": "折叠屏/AI/生态",
        "delta": "维度升维",
        "tone": "up"
      }
    ],
    "actions": [
      "转变沟通姿态：从“征服者叙事”转向“本地价值共建者”叙事，以谦逊的强者姿态进行传播。",
      "构建信任飞地：通过数据透明化、ESG承诺与长期本土投资，以“超本地化”运营积累深层信任。",
      "聚焦价值创新：在折叠形态、端侧AI、跨设备生态等维度打造“人无我有”的差异化体验，而非参数内卷。",
      "善用“智慧外脑”：高度重视专业舆论场的风险预警，将其纳入企业战略风险评估与预案体系。"
    ]
  },
  "themeTokens": {
    "typography": {
      "fontFamily": {
        "sans": "'PingFang SC', 'Microsoft YaHei', 'Helvetica Neue', Arial, sans-serif",
        "mono": "'SF Mono', 'Monaco', 'Consolas', monospace"
      },
      "fontSize": {
        "h1": "2.5rem",
        "h2": "2rem",
        "h3": "1.5rem",
        "body": "1rem",
        "small": "0.875rem"
      },
      "lineHeight": {
        "tight": 1.2,
        "normal": 1.6,
        "relaxed": 1.8
      }
    },
    "spacing": {
      "section": "4rem",
      "subsection": "2.5rem",
      "paragraph": "1.5rem"
    },
    "colors": {
      "primary": {
        "main": "#1a56db",
        "light": "#3f83f8",
        "dark": "#1e429f"
      },
      "secondary": {
        "main": "#046c4e",
        "light": "#0e9f6e",
        "dark": "03543f"
      },
      "neutral": {
        "100": "#f7fafc",
        "200": "#edf2f7",
        "700": "#4a5568",
        "900": "#1a202c"
      },
      "semantic": {
        "positive": "#0e9f6e",
        "caution": "#d69e2e",
        "critical": "#c53030"
      }
    },
    "darkMode": {
      "background": "#1a202c",
      "surface": "#2d3748",
      "onSurface": "#e2e8f0",
      "primary": "#63b3ed"
    }
  },
  "tocPlan": [
    {
      "chapterId": "S1",
      "anchor": "section-1-0",
      "display": "一、 市场态势总览：冰火交织的竞争图景与核心结论",
      "description": "概述中国科技品牌在日韩市场的整体表现、竞争格局与核心挑战，提炼关键数据与首要策略建议。"
    },
    {
      "chapterId": "S2",
      "anchor": "section-2-0",
      "display": "二、 声量与认知分析：舆论场的演进与品牌叙事变迁",
      "description": "分析品牌在日韩及国内舆论场的声量份额、情感演变轨迹，以及从“性价比屠夫”到“生态破壁者”的认知范式转移。"
    },
    {
      "chapterId": "S3",
      "anchor": "section-3-0",
      "display": "三、 关键动态时间线：我方与竞争对手的战略动作复盘",
      "description": "梳理近期影响市场格局的关键事件、产品发布、营销战役及合规动态，构建竞争演进的时序脉络。"
    },
    {
      "chapterId": "S4",
      "anchor": "section-4-0",
      "display": "四、 产品口碑与用户反馈：体验层面的攻防战",
      "description": "对比分析各品牌在产品情感分布、核心优缺点及功能卖点讨论热度上的表现，洞察用户体验层面的得失。"
    },
    {
      "chapterId": "S5",
      "anchor": "section-5-0",
      "display": "五、 营销与传播策略：本土化深耕与价值传递",
      "description": "剖析重大营销战役、核心传播议题及KOL合作策略的成败，评估品牌在文化沟通与价值叙事上的有效性。"
    },
    {
      "chapterId": "S6",
      "anchor": "section-6-0",
      "display": "六、 竞争机会与威胁识别：破局点与风险预警",
      "description": "系统识别当前市场存在的空白机会点、潜在威胁与风险，并提出基于差异化定位的破局思路。",
      "allowPest": true
    },
    {
      "chapterId": "S7",
      "anchor": "section-7-0",
      "display": "七、 综合结论与战略建议",
      "description": "总结全文核心发现，提炼可供借鉴的竞争策略，并针对不同竞争情境提出具体的行动建议与反制措施。",
      "allowSwot": true
    }
  ],
  "layoutNotes": [
    "目录页与各章节一级标题（H1）使用统一字号（2.5rem），确保视觉层级的清晰与一致。",
    "正文部分采用宽松的行高（1.6-1.8）与段落间距（1.5rem），提升长文阅读的舒适度。",
    "关键数据与核心结论优先使用Chart.js图表、KPI指标卡或对比表格进行可视化呈现，增强报告的说服力与可读性。",
    "SWOT分析块仅用于第七章“综合结论与战略建议”，PEST分析块仅用于第六章“竞争机会与威胁识别”，二者不共存于同一章节。",
    "报告整体色调以科技蓝（#1a56db）与生态绿（#046c4e）为主，分别象征技术创新与可持续增长，并已预设暗黑模式兼容色值。",
    "各章节内部结构（如1.1, 1.2）严格遵循模板二级大纲，仅对一级目录标题进行了中文叙事化优化，未增删任何分析模块。"
  ]
}